ufn/__init__.py
ufn/__main__.py
ufn/utils.py
ufn-1.1.0.dist-info/LICENSE
ufn-1.1.0.dist-info/METADATA
ufn-1.1.0.dist-info/WHEEL
ufn-1.1.0.dist-info/top_level.txt
ufn-1.1.0.dist-info/RECORD
