Metadata-Version: 2.1
Name: ufn
Version: 1.1.0
Summary: upload for nas
Home-page: https://github.com/sduwfc/ufn
Author: kilmu
Author-email: mail@wfc.im
License: UNKNOWN
Platform: UNKNOWN
Classifier: Development Status :: 3 - Alpha
Classifier: Intended Audience :: Developers
Classifier: License :: OSI Approved :: MIT License
Classifier: Programming Language :: Python :: 3
Classifier: Programming Language :: Python :: 3.6
Classifier: Programming Language :: Python :: 3.7
Classifier: Programming Language :: Python :: 3.8
Classifier: Programming Language :: Python :: 3.9
License-File: LICENSE
Requires-Dist: requests
Requires-Dist: tqdm
Requires-Dist: requests-toolbelt
